Workbook

Sheet enterprise efficiency
A1: variables
A2: investment | B2: 14000
A3: revenue | B3: 8000
A4: cost | B4: 2000
A5: profit | B5: =B3-B4
A7: efficiency
A8: investment | B8: =(B5-B2)/B2
A9: sales | B9: =B5/B3
A10: payback period | B10: =B2/B5*12
A12: comparison with bank
A13: deposit rate | B13: 0.03
A14: deposit income | B14: =B2*(1+B13*1)
A15: net income | B15: =B14-B2
A16: difference | B16: =B5-B15
A17: conclusion | B17: =GT(B16,0) | C17: the project is more profitable if TRUE
A19: compound interest | B19: revenue | C19: cost | D19: profit FV | E19: profit FV with deposit
A20: year 1 | B20: 8000 | C20: 541.43 | D20: =B20-C20 | E20: =D20*(1+B13)^3
A21: year 2 | B21: 8000 | C21: 550 | D21: =B21-C21 | E21: =D21*(1+B13)^2
A22: year 3 | B22: 8000 | C22: 880 | D22: =B22-C22 | E22: =D22*(1+B13)^1
A23: year 4 | B23: 8000 | C23: 888 | D23: =B23-C23 | E23: =D23*(1+B13)^0
A24: total | B24: =SUM(B20:B23) | C24: =SUM(C20:C23) | D24: =SUM(D20:D23) | E24: =SUM(E20:E23)
A26: bank effect
A27: bank income | B27: =B2*(1+B13)^4-B2
A28: project income | B28: =E24-B2
A29: difference | B29: =B28-B27

Sheet turnover reduction measures
A1: variables
A2: average number of employees | B2: 454
A3: number of dismissed employees | B3: 343
A4: turnover reduction factor | B4: 0.12
A5: average salary | B5: 70
A6: recruitment cost as share of salary | B6: 0.25 | C6: =B5*B6
A8: turnover | B8: =B3/B2
A9: FV | B9: =B8*(1-B4)
A10: FV of dismissed employees per year | B10: =B2*B9
A11: social result | B11: =B8-B9
A13: total recruitment costs | B13: =B3*C6
A14: FV | B14: =B10*C6
A15: FV reduction | B15: =B13-B14

Sheet implementation efficiency
A1: variables
A2: implementation costs | B2: 30
A4: profitability | B4: costs | C4: sales | D4: cost share in revenue
A5: year 1 | B5: ='enterprise efficiency'!D20/'enterprise efficiency'!C20 | C5: ='enterprise efficiency'!D20/'enterprise efficiency'!B20 | D5: ='enterprise efficiency'!C20/'enterprise efficiency'!B20
A6: year 2 | B6: ='enterprise efficiency'!D21/'enterprise efficiency'!C21 | C6: ='enterprise efficiency'!D21/'enterprise efficiency'!B21 | D6: ='enterprise efficiency'!C21/'enterprise efficiency'!B21
A7: year 3 | B7: ='enterprise efficiency'!D22/'enterprise efficiency'!C22 | C7: ='enterprise efficiency'!D22/'enterprise efficiency'!B22 | D7: ='enterprise efficiency'!C22/'enterprise efficiency'!B22
A8: year 4 | B8: ='enterprise efficiency'!D23/'enterprise efficiency'!C23 | C8: ='enterprise efficiency'!D23/'enterprise efficiency'!B23 | D8: ='enterprise efficiency'!C23/'enterprise efficiency'!B23
A9: average | B9: =AVERAGE(B5:B8) | C9: =AVERAGE(C5:C8) | D9: =AVERAGE(D5:D8)
A11: average indicators | B11: before implementation | C11: after implementation
A12: revenue | B12: =AVERAGE('enterprise efficiency'!B20:B23) | C12: =AVERAGE('enterprise efficiency'!B20:B23)
A13: costs | B13: =AVERAGE('enterprise efficiency'!C20:C23)+'turnover reduction measures'!B13 | C13: =AVERAGE('enterprise efficiency'!C20:C23)+'turnover reduction measures'!B14
A14: profit | B14: =B12-B13 | C14: =C12-C13
A15: cost profitability | B15: =B14/B13 | C15: =C14/C13
A16: sales profitability | B16: =B14/B12 | C16: =C14/C12
A18: profit increase | B18: =C14-B14
A19: implementation effect | B19: =B18-B2
A20: efficiency | B20: =B19/B2 | C20: %
